.DS_Store
DBDIpy/__init__.py
DBDIpy/align_spectra.py
DBDIpy/dbdipy_auxiliaries.py
DBDIpy/export_to_spectra.py
DBDIpy/identify_adducts.py
DBDIpy/identify_adducts_MS2.py
DBDIpy/identify_adducts_XIC.py
DBDIpy/impute_intensities.py
DBDIpy/plot_adducts.py
DBDIpy/plot_adducts_MS2.py
DBDIpy/plot_adducts_XIC.py
DBDIpy/propose_adducts.py
DBDIpy/tests/testLW.py
DBDIpy/tests/test_align_spectra.py
DBDIpy/tests/test_dbdipy_auxiliaries.py
DBDIpy/tests/test_export_to_spectra.py
DBDIpy/tests/test_identify_adducts.py
DBDIpy/tests/test_identify_adducts_MS2.py
DBDIpy/tests/test_identify_adducts_XIC.py
DBDIpy/tests/test_impute_intensities.py
DBDIpy/tests/test_plot_adducts.py
DBDIpy/tests/test_plot_adducts_MS2.py
DBDIpy/tests/test_plot_adducts_XIC.py
DBDIpy/tests/test_propose_adducts.py
dbdiLW/__init__.py
dbdiLW/alignment.py
dbdiLW/correlation_module.py
dbdiLW/imputation module.py
dbdiLW/plotting_modull.py
dbdiLW/testfun.py
dbdiLW/tests/__init__.py
dbdiLW/tests/tests_correlation_module.py
dbdiLW/tests/tests_imputation module.py
dbdiLW/tests/tests_plotting_modull.py
DBDIpy-2.0.dist-info/METADATA
DBDIpy-2.0.dist-info/WHEEL
DBDIpy-2.0.dist-info/top_level.txt
DBDIpy-2.0.dist-info/RECORD
