Metadata-Version: 2.1
Name: DBDIpy
Version: 2.0
Summary: A python package for the curation and interpretation of datasets from plasma ionisation mass spectrometric.
Home-page: https://github.com/leopold-weidner/DBDIpy
Author: Leopold Weidner
Author-email: leopold.weidner@tum.de
License: docs/license.txt
Keywords: python,bioinformatics,mass spectrometry,metabolomics,foodomics
Classifier: Intended Audience :: Developers
Classifier: License :: OSI Approved :: MIT License
Classifier: Programming Language :: Python
Classifier: Programming Language :: Python :: 3
Classifier: Programming Language :: Python :: 3.7
Classifier: Programming Language :: Python :: 3.8
Classifier: Programming Language :: Python :: 3.9
Classifier: Programming Language :: Python :: 3.10
Classifier: Operating System :: OS Independent
Requires-Dist: pandas
Requires-Dist: numpy
Requires-Dist: tqdm
Requires-Dist: matchms
Requires-Dist: matplotlib
Requires-Dist: pytest
Requires-Dist: scipy
Requires-Dist: feather-format
